zsniff/__init__.py
zsniff/cli.py
zsniff/core.py
zsniff/models.py
zsniff/parsers.py
zsniff/processor.py
zsniff/utils.py
zsniff-0.0.1.dist-info/METADATA
zsniff-0.0.1.dist-info/WHEEL
zsniff-0.0.1.dist-info/entry_points.txt
zsniff-0.0.1.dist-info/licenses/LICENSE
zsniff-0.0.1.dist-info/RECORD
