Metadata-Version: 2.4
Name: zsniff
Version: 0.0.1
Summary: Passive ZeroMQ protocol analyzer and traffic sniffer
Project-URL: Homepage, https://github.com/ajcasagrande/zsniff
Project-URL: Bug Tracker, https://github.com/ajcasagrande/zsniff/issues
Author: Anthony Casagrande
License: MIT
License-File: LICENSE
Classifier: Development Status :: 4 - Beta
Classifier: Intended Audience :: Developers
Classifier: Intended Audience :: System Administrators
Classifier: License :: OSI Approved :: MIT License
Classifier: Programming Language :: Python :: 3
Classifier: Programming Language :: Python :: 3.8
Classifier: Programming Language :: Python :: 3.9
Classifier: Programming Language :: Python :: 3.10
Classifier: Programming Language :: Python :: 3.11
Classifier: Programming Language :: Python :: 3.12
Classifier: Programming Language :: Python :: 3.13
Classifier: Topic :: System :: Networking :: Monitoring
Requires-Python: >=3.8
Requires-Dist: demjson3>=3.0.5
Requires-Dist: pydantic>=2.0.0
Requires-Dist: rich>=12.0.0
Requires-Dist: scapy>=2.4.5
Provides-Extra: dev
Requires-Dist: black>=23.0.0; extra == 'dev'
Requires-Dist: isort>=5.12.0; extra == 'dev'
Requires-Dist: pytest-cov>=4.0.0; extra == 'dev'
Requires-Dist: pytest>=7.0.0; extra == 'dev'
Requires-Dist: ruff>=0.0.270; extra == 'dev'
